account/__init__.py
account/admin.py
account/apps.py
account/forms.py
account/models.py
account/tests.py
account/urls.py
account/views.py
account/migrations/0001_initial.py
account/migrations/__init__.py
account/templates/account/login.html
account/templates/account/signup.html
draj_auth_module-1.3.dist-info/LICENSE
draj_auth_module-1.3.dist-info/METADATA
draj_auth_module-1.3.dist-info/WHEEL
draj_auth_module-1.3.dist-info/top_level.txt
draj_auth_module-1.3.dist-info/RECORD
