Metadata-Version: 2.1
Name: draj-auth-module
Version: 1.3
Summary: django user login register and logout module
Home-page: https://www.trootech.com/
Author: Dharmrajsinh Gohil
Author-email: dharmrajsinh.gohil@trootech.com
Maintainer: Dharmrajsinh
Maintainer-email: dharmrajsinh.gohil@trootech.com
License: MIT
Keywords: django auth module
Classifier: Development Status :: 4 - Beta
Classifier: Environment :: Web Environment
Classifier: Intended Audience :: Developers
Classifier: License :: OSI Approved :: MIT License
Classifier: Operating System :: OS Independent
Classifier: Programming Language :: Python :: 3 :: Only
Classifier: Programming Language :: Python :: 3.8
Classifier: Programming Language :: Python :: Implementation :: CPython
Classifier: Topic :: Software Development :: Libraries :: Application Frameworks
Classifier: Topic :: Software Development :: Libraries :: Python Modules
License-File: LICENSE
